Workbook

Sheet LEGGIMI
A1: MONITOR CHALLENGE / FUNDED - registro di prelievi, profitti e muri
A2: Creato il 26/08/2026. Numeri di riferimento: analisi di casa sul dataset 481 giorni (ANALISI_DIAL_TAGLIE e ANALISI_DD_TOTALE del 26/08/2026, repo GitHub, branch lavoro).
A4: COME SI USA
A5: 1. Foglio IMPOSTAZIONI: compila le celle GIALLE con i dati della prop scelta (taglia, muri, split, costo). Tutto il resto si calcola da solo.
A6: 2. Foglio GIORNALIERO: una riga al giorno, a mercati chiusi. Compili SOLO le 3 colonne gialle: data, equity di chiusura, eventuale prelievo del giorno. Facoltativa: equity minima intraday se la leggi dal terminale (i muri delle prop guardano il FLOTTANTE).
A7: 3. Foglio PRELIEVI: una riga per ogni payout richiesto.
A8: 4. Foglio DASHBOARD: solo lettura, si aggiorna da solo.
A10: COLORI: GIALLO = cella da compilare a mano. Testo BLU = valore inserito a mano. Testo NERO = formula (non toccare). Testo VERDE = collegamento a un altro foglio.
A11: La riga 2 del GIORNALIERO e la riga 2 dei PRELIEVI sono ESEMPI con valori finti: sovrascrivile coi tuoi dati veri.
A13: LE DUE COSE DA SAPERE SUI MURI
A14: - Il muro GIORNALIERO si calcola sull'equity di inizio giornata: la colonna 'Perdita max oggi' te lo dice gia' in euro, giorno per giorno.
A15: - Il muro TOTALE (statico) si calcola sul saldo INIZIALE: quando PRELEVI, l'equity scende e ti AVVICINI al muro. E' il motivo della politica del buffer: prelevare si', ma lasciando un cuscino (vedi DASHBOARD, riga 'cuscino sopra il saldo iniziale').
A17: ATTENZIONE: questo registro lavora sui numeri di CHIUSURA che inserisci tu. Il flottante intraday lo vede solo la colonna facoltativa 'Equity minima intraday': se la compili, il controllo dei muri diventa molto piu' fedele a quello della prop.

Sheet IMPOSTAZIONI
A1: IMPOSTAZIONI DELLA PROP (celle gialle = da compilare)
A3: Taglia del conto (saldo iniziale) | B3: 100000 | C3: Compilare con la taglia comprata (es. 100000, 200000...)
A4: Muro giornaliero (% dell'equity di inizio giornata) | B4: 0.05 | C4: Dalla scheda regole della prop. Standard: 5%
A5: Muro totale statico (% del saldo iniziale) | B5: 0.1 | C5: Dalla scheda regole. Standard: 10%. Se la prop ha muro TRAILING: NON comprarla (analisi 26/08: picco-valle 6,37% romperebbe un trailing 6% anche sui chiusi)
A6: Profit split (quota tua sui profitti) | B6: 0.85 | C6: Dalla scheda payout della prop scelta (tipico 80-90%)
A7: Costo della challenge | B7: 500 | C7: Prezzo pagato (per il calcolo del ROI in DASHBOARD)
A8: Dial di rischio in campo | B8: 1 | C8: Firmato: challenge a 1,00. Proposta due-dial: funded a 0,74 (da firmare all'apertura)
A10: Muro totale in euro (sotto questo saldo = conto perso) | B10: =B2*(1-B4) | C10: Formula: saldo iniziale x (1 - muro totale)
A11: Perdita giornaliera limite sul saldo pieno | B11: =B2*B3 | C11: Formula: saldo iniziale x muro giornaliero (il valore vivo, giorno per giorno, sta nel GIORNALIERO)
A13: RIFERIMENTI MISURATI DI CASA (non toccare)
A14: Peggior giornata attesa (chiusi, dial 1,00) | B14: -0.0474 | C14: ANALISI_DIAL_TAGLIE 26/08/2026 su 481 giorni
A15: Peggior DD totale atteso in challenge (chiusi) | B15: -0.0637 | C15: ANALISI_DD_TOTALE 26/08/2026: worst su 481 partenze; p99 -5,83%
A16: Guardian: pausa / emergenza (perdita giornaliera) | B16: 4,0% / 4,9% | C16: Pacchetto firmato il 18/08/2026

Sheet GIORNALIERO
A1: Data | B1: Equity chiusura (EUR) | C1: Prelievo del giorno (EUR) | D1: Equity min intraday (EUR, facolt.) | E1: P&L del giorno (EUR) | F1: P&L del giorno (%) | G1: Perdita max oggi (EUR, muro 5%) | H1: Margine sul muro giornaliero (EUR) | I1: Distanza dal muro totale (EUR) | J1: Cuscino sopra saldo iniziale (EUR) | K1: ESITO
A2: =DATE(2026,10,1) | B2: 100650 | D2: 99800 | E2: =IF($B2="","",B2-IF(ROW()=2,IMPOSTAZIONI!$B$3,B1)+IF(C2="",0,C2)) | F2: =IF($B2="","",E2/IF(ROW()=2,IMPOSTAZIONI!$B$3,B1)) | G2: =IF($B2="","",IF(ROW()=2,IMPOSTAZIONI!$B$3,B1)*IMPOSTAZIONI!$B$4) | H2: =IF($B2="","",G2+MIN(0,IF(D2="",E2,MIN(E2,D2-IF(ROW()=2,IMPOSTAZIONI!$B$3,B1))))) | I2: =IF($B2="","",IF(D2="",B2,MIN(B2,D2))-IMPOSTAZIONI!$B$10) | J2: =IF($B2="","",B2-IMPOSTAZIONI!$B$3) | K2: =IF($B2="","",IF(OR(H2<=0,I2<=0),"VIOLAZIONE",IF(OR(H2<IF(ROW()=2,IMPOSTAZIONI!$B$3,B1)*0.01,I2<IMPOSTAZIONI!$B$3*0.02),"ATTENZIONE","OK")))
E3: =IF($B3="","",B3-IF(ROW()=2,IMPOSTAZIONI!$B$3,B2)+IF(C3="",0,C3)) | F3: =IF($B3="","",E3/IF(ROW()=2,IMPOSTAZIONI!$B$3,B2)) | G3: =IF($B3="","",IF(ROW()=2,IMPOSTAZIONI!$B$3,B2)*IMPOSTAZIONI!$B$4) | H3: =IF($B3="","",G3+MIN(0,IF(D3="",E3,MIN(E3,D3-IF(ROW()=2,IMPOSTAZIONI!$B$3,B2))))) | I3: =IF($B3="","",IF(D3="",B3,MIN(B3,D3))-IMPOSTAZIONI!$B$10) | J3: =IF($B3="","",B3-IMPOSTAZIONI!$B$3) | K3: =IF($B3="","",IF(OR(H3<=0,I3<=0),"VIOLAZIONE",IF(OR(H3<IF(ROW()=2,IMPOSTAZIONI!$B$3,B2)*0.01,I3<IMPOSTAZIONI!$B$3*0.02),"ATTENZIONE","OK")))
E4: =IF($B4="","",B4-IF(ROW()=2,IMPOSTAZIONI!$B$3,B3)+IF(C4="",0,C4)) | F4: =IF($B4="","",E4/IF(ROW()=2,IMPOSTAZIONI!$B$3,B3)) | G4: =IF($B4="","",IF(ROW()=2,IMPOSTAZIONI!$B$3,B3)*IMPOSTAZIONI!$B$4) | H4: =IF($B4="","",G4+MIN(0,IF(D4="",E4,MIN(E4,D4-IF(ROW()=2,IMPOSTAZIONI!$B$3,B3))))) | I4: =IF($B4="","",IF(D4="",B4,MIN(B4,D4))-IMPOSTAZIONI!$B$10) | J4: =IF($B4="","",B4-IMPOSTAZIONI!$B$3) | K4: =IF($B4="","",IF(OR(H4<=0,I4<=0),"VIOLAZIONE",IF(OR(H4<IF(ROW()=2,IMPOSTAZIONI!$B$3,B3)*0.01,I4<IMPOSTAZIONI!$B$3*0.02),"ATTENZIONE","OK")))
E5: =IF($B5="","",B5-IF(ROW()=2,IMPOSTAZIONI!$B$3,B4)+IF(C5="",0,C5)) | F5: =IF($B5="","",E5/IF(ROW()=2,IMPOSTAZIONI!$B$3,B4)) | G5: =IF($B5="","",IF(ROW()=2,IMPOSTAZIONI!$B$3,B4)*IMPOSTAZIONI!$B$4) | H5: =IF($B5="","",G5+MIN(0,IF(D5="",E5,MIN(E5,D5-IF(ROW()=2,IMPOSTAZIONI!$B$3,B4))))) | I5: =IF($B5="","",IF(D5="",B5,MIN(B5,D5))-IMPOSTAZIONI!$B$10) | J5: =IF($B5="","",B5-IMPOSTAZIONI!$B$3) | K5: =IF($B5="","",IF(OR(H5<=0,I5<=0),"VIOLAZIONE",IF(OR(H5<IF(ROW()=2,IMPOSTAZIONI!$B$3,B4)*0.01,I5<IMPOSTAZIONI!$B$3*0.02),"ATTENZIONE","OK")))
E6: =IF($B6="","",B6-IF(ROW()=2,IMPOSTAZIONI!$B$3,B5)+IF(C6="",0,C6)) | F6: =IF($B6="","",E6/IF(ROW()=2,IMPOSTAZIONI!$B$3,B5)) | G6: =IF($B6="","",IF(ROW()=2,IMPOSTAZIONI!$B$3,B5)*IMPOSTAZIONI!$B$4) | H6: =IF($B6="","",G6+MIN(0,IF(D6="",E6,MIN(E6,D6-IF(ROW()=2,IMPOSTAZIONI!$B$3,B5))))) | I6: =IF($B6="","",IF(D6="",B6,MIN(B6,D6))-IMPOSTAZIONI!$B$10) | J6: =IF($B6="","",B6-IMPOSTAZIONI!$B$3) | K6: =IF($B6="","",IF(OR(H6<=0,I6<=0),"VIOLAZIONE",IF(OR(H6<IF(ROW()=2,IMPOSTAZIONI!$B$3,B5)*0.01,I6<IMPOSTAZIONI!$B$3*0.02),"ATTENZIONE","OK")))
E7: =IF($B7="","",B7-IF(ROW()=2,IMPOSTAZIONI!$B$3,B6)+IF(C7="",0,C7)) | F7: =IF($B7="","",E7/IF(ROW()=2,IMPOSTAZIONI!$B$3,B6)) | G7: =IF($B7="","",IF(ROW()=2,IMPOSTAZIONI!$B$3,B6)*IMPOSTAZIONI!$B$4) | H7: =IF($B7="","",G7+MIN(0,IF(D7="",E7,MIN(E7,D7-IF(ROW()=2,IMPOSTAZIONI!$B$3,B6))))) | I7: =IF($B7="","",IF(D7="",B7,MIN(B7,D7))-IMPOSTAZIONI!$B$10) | J7: =IF($B7="","",B7-IMPOSTAZIONI!$B$3) | K7: =IF($B7="","",IF(OR(H7<=0,I7<=0),"VIOLAZIONE",IF(OR(H7<IF(ROW()=2,IMPOSTAZIONI!$B$3,B6)*0.01,I7<IMPOSTAZIONI!$B$3*0.02),"ATTENZIONE","OK")))
E8: =IF($B8="","",B8-IF(ROW()=2,IMPOSTAZIONI!$B$3,B7)+IF(C8="",0,C8)) | F8: =IF($B8="","",E8/IF(ROW()=2,IMPOSTAZIONI!$B$3,B7)) | G8: =IF($B8="","",IF(ROW()=2,IMPOSTAZIONI!$B$3,B7)*IMPOSTAZIONI!$B$4) | H8: =IF($B8="","",G8+MIN(0,IF(D8="",E8,MIN(E8,D8-IF(ROW()=2,IMPOSTAZIONI!$B$3,B7))))) | I8: =IF($B8="","",IF(D8="",B8,MIN(B8,D8))-IMPOSTAZIONI!$B$10) | J8: =IF($B8="","",B8-IMPOSTAZIONI!$B$3) | K8: =IF($B8="","",IF(OR(H8<=0,I8<=0),"VIOLAZIONE",IF(OR(H8<IF(ROW()=2,IMPOSTAZIONI!$B$3,B7)*0.01,I8<IMPOSTAZIONI!$B$3*0.02),"ATTENZIONE","OK")))
E9: =IF($B9="","",B9-IF(ROW()=2,IMPOSTAZIONI!$B$3,B8)+IF(C9="",0,C9)) | F9: =IF($B9="","",E9/IF(ROW()=2,IMPOSTAZIONI!$B$3,B8)) | G9: =IF($B9="","",IF(ROW()=2,IMPOSTAZIONI!$B$3,B8)*IMPOSTAZIONI!$B$4) | H9: =IF($B9="","",G9+MIN(0,IF(D9="",E9,MIN(E9,D9-IF(ROW()=2,IMPOSTAZIONI!$B$3,B8))))) | I9: =IF($B9="","",IF(D9="",B9,MIN(B9,D9))-IMPOSTAZIONI!$B$10) | J9: =IF($B9="","",B9-IMPOSTAZIONI!$B$3) | K9: =IF($B9="","",IF(OR(H9<=0,I9<=0),"VIOLAZIONE",IF(OR(H9<IF(ROW()=2,IMPOSTAZIONI!$B$3,B8)*0.01,I9<IMPOSTAZIONI!$B$3*0.02),"ATTENZIONE","OK")))
E10: =IF($B10="","",B10-IF(ROW()=2,IMPOSTAZIONI!$B$3,B9)+IF(C10="",0,C10)) | F10: =IF($B10="","",E10/IF(ROW()=2,IMPOSTAZIONI!$B$3,B9)) | G10: =IF($B10="","",IF(ROW()=2,IMPOSTAZIONI!$B$3,B9)*IMPOSTAZIONI!$B$4) | H10: =IF($B10="","",G10+MIN(0,IF(D10="",E10,MIN(E10,D10-IF(ROW()=2,IMPOSTAZIONI!$B$3,B9))))) | I10: =IF($B10="","",IF(D10="",B10,MIN(B10,D10))-IMPOSTAZIONI!$B$10) | J10: =IF($B10="","",B10-IMPOSTAZIONI!$B$3) | K10: =IF($B10="","",IF(OR(H10<=0,I10<=0),"VIOLAZIONE",IF(OR(H10<IF(ROW()=2,IMPOSTAZIONI!$B$3,B9)*0.01,I10<IMPOSTAZIONI!$B$3*0.02),"ATTENZIONE","OK")))
E11: =IF($B11="","",B11-IF(ROW()=2,IMPOSTAZIONI!$B$3,B10)+IF(C11="",0,C11)) | F11: =IF($B11="","",E11/IF(ROW()=2,IMPOSTAZIONI!$B$3,B10)) | G11: =IF($B11="","",IF(ROW()=2,IMPOSTAZIONI!$B$3,B10)*IMPOSTAZIONI!$B$4) | H11: =IF($B11="","",G11+MIN(0,IF(D11="",E11,MIN(E11,D11-IF(ROW()=2,IMPOSTAZIONI!$B$3,B10))))) | I11: =IF($B11="","",IF(D11="",B11,MIN(B11,D11))-IMPOSTAZIONI!$B$10) | J11: =IF($B11="","",B11-IMPOSTAZIONI!$B$3) | K11: =IF($B11="","",IF(OR(H11<=0,I11<=0),"VIOLAZIONE",IF(OR(H11<IF(ROW()=2,IMPOSTAZIONI!$B$3,B10)*0.01,I11<IMPOSTAZIONI!$B$3*0.02),"ATTENZIONE","OK")))
E12: =IF($B12="","",B12-IF(ROW()=2,IMPOSTAZIONI!$B$3,B11)+IF(C12="",0,C12)) | F12: =IF($B12="","",E12/IF(ROW()=2,IMPOSTAZIONI!$B$3,B11)) | G12: =IF($B12="","",IF(ROW()=2,IMPOSTAZIONI!$B$3,B11)*IMPOSTAZIONI!$B$4) | H12: =IF($B12="","",G12+MIN(0,IF(D12="",E12,MIN(E12,D12-IF(ROW()=2,IMPOSTAZIONI!$B$3,B11))))) | I12: =IF($B12="","",IF(D12="",B12,MIN(B12,D12))-IMPOSTAZIONI!$B$10) | J12: =IF($B12="","",B12-IMPOSTAZIONI!$B$3) | K12: =IF($B12="","",IF(OR(H12<=0,I12<=0),"VIOLAZIONE",IF(OR(H12<IF(ROW()=2,IMPOSTAZIONI!$B$3,B11)*0.01,I12<IMPOSTAZIONI!$B$3*0.02),"ATTENZIONE","OK")))
E13: =IF($B13="","",B13-IF(ROW()=2,IMPOSTAZIONI!$B$3,B12)+IF(C13="",0,C13)) | F13: =IF($B13="","",E13/IF(ROW()=2,IMPOSTAZIONI!$B$3,B12)) | G13: =IF($B13="","",IF(ROW()=2,IMPOSTAZIONI!$B$3,B12)*IMPOSTAZIONI!$B$4) | H13: =IF($B13="","",G13+MIN(0,IF(D13="",E13,MIN(E13,D13-IF(ROW()=2,IMPOSTAZIONI!$B$3,B12))))) | I13: =IF($B13="","",IF(D13="",B13,MIN(B13,D13))-IMPOSTAZIONI!$B$10) | J13: =IF($B13="","",B13-IMPOSTAZIONI!$B$3) | K13: =IF($B13="","",IF(OR(H13<=0,I13<=0),"VIOLAZIONE",IF(OR(H13<IF(ROW()=2,IMPOSTAZIONI!$B$3,B12)*0.01,I13<IMPOSTAZIONI!$B$3*0.02),"ATTENZIONE","OK")))
E14: =IF($B14="","",B14-IF(ROW()=2,IMPOSTAZIONI!$B$3,B13)+IF(C14="",0,C14)) | F14: =IF($B14="","",E14/IF(ROW()=2,IMPOSTAZIONI!$B$3,B13)) | G14: =IF($B14="","",IF(ROW()=2,IMPOSTAZIONI!$B$3,B13)*IMPOSTAZIONI!$B$4) | H14: =IF($B14="","",G14+MIN(0,IF(D14="",E14,MIN(E14,D14-IF(ROW()=2,IMPOSTAZIONI!$B$3,B13))))) | I14: =IF($B14="","",IF(D14="",B14,MIN(B14,D14))-IMPOSTAZIONI!$B$10) | J14: =IF($B14="","",B14-IMPOSTAZIONI!$B$3) | K14: =IF($B14="","",IF(OR(H14<=0,I14<=0),"VIOLAZIONE",IF(OR(H14<IF(ROW()=2,IMPOSTAZIONI!$B$3,B13)*0.01,I14<IMPOSTAZIONI!$B$3*0.02),"ATTENZIONE","OK")))
... E251: =IF($B251="","",B251-IF(ROW()=2,IMPOSTAZIONI!$B$3,B250)+IF(C251="",0,C251)) | F251: =IF($B251="","",E251/IF(ROW()=2,IMPOSTAZIONI!$B$3,B250)) | G251: =IF($B251="","",IF(ROW()=2,IMPOSTAZIONI!$B$3,B250)*IMPOSTAZIONI!$B$4) | H251: =IF($B251="","",G251+MIN(0,IF(D251="",E251,MIN(E251,D251-IF(ROW()=2,IMPOSTAZIONI!$B$3,B250))))) | I251: =IF($B251="","",IF(D251="",B251,MIN(B251,D251))-IMPOSTAZIONI!$B$10) | J251: =IF($B251="","",B251-IMPOSTAZIONI!$B$3) | K251: =IF($B251="","",IF(OR(H251<=0,I251<=0),"VIOLAZIONE",IF(OR(H251<IF(ROW()=2,IMPOSTAZIONI!$B$3,B250)*0.01,I251<IMPOSTAZIONI!$B$3*0.02),"ATTENZIONE","OK")))

Sheet PRELIEVI
A1: Data richiesta | B1: Importo richiesto (EUR) | C1: Quota tua (EUR, x split) | D1: Data accredito (facolt.) | E1: Cumulato prelevato (EUR) | F1: Note
A2: =DATE(2026,10,20) | B2: 3000 | C2: =IF(B2="","",B2*IMPOSTAZIONI!$B$6) | E2: =IF(B2="","",SUM($B$2:B2)) | F2: RIGA DI ESEMPIO: sovrascrivere
C3: =IF(B3="","",B3*IMPOSTAZIONI!$B$6) | E3: =IF(B3="","",SUM($B$2:B3))
C4: =IF(B4="","",B4*IMPOSTAZIONI!$B$6) | E4: =IF(B4="","",SUM($B$2:B4))
C5: =IF(B5="","",B5*IMPOSTAZIONI!$B$6) | E5: =IF(B5="","",SUM($B$2:B5))
C6: =IF(B6="","",B6*IMPOSTAZIONI!$B$6) | E6: =IF(B6="","",SUM($B$2:B6))
C7: =IF(B7="","",B7*IMPOSTAZIONI!$B$6) | E7: =IF(B7="","",SUM($B$2:B7))
C8: =IF(B8="","",B8*IMPOSTAZIONI!$B$6) | E8: =IF(B8="","",SUM($B$2:B8))
C9: =IF(B9="","",B9*IMPOSTAZIONI!$B$6) | E9: =IF(B9="","",SUM($B$2:B9))
C10: =IF(B10="","",B10*IMPOSTAZIONI!$B$6) | E10: =IF(B10="","",SUM($B$2:B10))
C11: =IF(B11="","",B11*IMPOSTAZIONI!$B$6) | E11: =IF(B11="","",SUM($B$2:B11))
C12: =IF(B12="","",B12*IMPOSTAZIONI!$B$6) | E12: =IF(B12="","",SUM($B$2:B12))
C13: =IF(B13="","",B13*IMPOSTAZIONI!$B$6) | E13: =IF(B13="","",SUM($B$2:B13))
C14: =IF(B14="","",B14*IMPOSTAZIONI!$B$6) | E14: =IF(B14="","",SUM($B$2:B14))
... C61: =IF(B61="","",B61*IMPOSTAZIONI!$B$6) | E61: =IF(B61="","",SUM($B$2:B61))

Sheet DASHBOARD
A1: DASHBOARD - si aggiorna da sola
A3: Giorni registrati | B3: =COUNT(GIORNALIERO!B2:B251)
A4: Equity attuale | B4: =IFERROR(INDEX(GIORNALIERO!B2:B251,COUNT(GIORNALIERO!$B$2:$B$251)),IMPOSTAZIONI!B3) | C4: ultima equity di chiusura inserita
A5: Profitto totale generato (equity + prelievi - iniziale) | B5: =IFERROR(INDEX(GIORNALIERO!B2:B251,COUNT(GIORNALIERO!$B$2:$B$251)),IMPOSTAZIONI!B3)+SUM(PRELIEVI!B2:B61)-IMPOSTAZIONI!B3
A6: Profitto totale in % della taglia | B6: =B5/IMPOSTAZIONI!B3 | C6: il target di challenge tipico e' +8/+10%
A7: Prelevato cumulato (lordo) | B7: =SUM(PRELIEVI!B2:B61)
A8: Incassato tuo (netto split) | B8: =SUM(PRELIEVI!B2:B61)*IMPOSTAZIONI!B6
A9: ROI sul costo della challenge | B9: =IFERROR(B8/IMPOSTAZIONI!B7,"-") | C9: incassato / costo
A11: Cuscino sopra il saldo iniziale | B11: =IFERROR(INDEX(GIORNALIERO!B2:B251,COUNT(GIORNALIERO!$B$2:$B$251)),IMPOSTAZIONI!B3)-IMPOSTAZIONI!B3 | C11: se negativo, sei sotto il saldo di partenza
A12: Distanza dal muro totale | B12: =IFERROR(INDEX(GIORNALIERO!B2:B251,COUNT(GIORNALIERO!$B$2:$B$251)),IMPOSTAZIONI!B3)-IMPOSTAZIONI!B10 | C12: sotto zero = conto perso
A13: Peggior giornata registrata (%) | B13: =IFERROR(MIN(GIORNALIERO!F2:F251),"-") | C13: confronto: atteso -4,74% (misurato sui chiusi)
A14: Peggior giornata registrata (EUR) | B14: =IFERROR(MIN(GIORNALIERO!E2:E251),"-")
A15: Giorni in ATTENZIONE | B15: =COUNTIF(GIORNALIERO!K2:K251,"ATTENZIONE") | C15: margine giornaliero sotto l1%% dell equity o cuscino totale sotto il 2%
A16: Giorni in VIOLAZIONE | B16: =COUNTIF(GIORNALIERO!K2:K251,"VIOLAZIONE") | C16: deve restare 0
